Metadata-Version: 2.1
Name: qinst
Version: 1.0.1
Summary: Quantum experiments related works instruments
Author: OrkeshNurbolat
Author-email: MG1922077@smail.nju.edu.cn
License: MIT
Classifier: License :: OSI Approved :: MIT License
Classifier: Programming Language :: Python :: 3.12
Classifier: Programming Language :: Python :: 3.11
Classifier: Programming Language :: Python :: 3.10
Classifier: Programming Language :: Python :: 3.9
Classifier: Programming Language :: Python :: 3.8
Classifier: Operating System :: OS Independent
Requires-Python: >=3.10
Provides-Extra: dev
